nodestream_akamai/__init__.py
nodestream_akamai/akamai_utils/__init__.py
nodestream_akamai/akamai_utils/addresses.py
nodestream_akamai/akamai_utils/appsec_client.py
nodestream_akamai/akamai_utils/client.py
nodestream_akamai/akamai_utils/cloudlet_client.py
nodestream_akamai/akamai_utils/cloudlets_v2_client.py
nodestream_akamai/akamai_utils/contract_client.py
nodestream_akamai/akamai_utils/cprg_client.py
nodestream_akamai/akamai_utils/cps_client.py
nodestream_akamai/akamai_utils/edgehostnames_client.py
nodestream_akamai/akamai_utils/edgeworkers_client.py
nodestream_akamai/akamai_utils/edns_client.py
nodestream_akamai/akamai_utils/gtm_client.py
nodestream_akamai/akamai_utils/iam_client.py
nodestream_akamai/akamai_utils/ivm_client.py
nodestream_akamai/akamai_utils/model.py
nodestream_akamai/akamai_utils/netstorage_client.py
nodestream_akamai/akamai_utils/property_client.py
nodestream_akamai/akamai_utils/siteshield_client.py
nodestream_akamai/apidiscovery/__init__.py
nodestream_akamai/apidiscovery/apidiscovery.py
nodestream_akamai/apidiscovery.yaml
nodestream_akamai/appsec-coverage.yaml
nodestream_akamai/appsec_coverage/__init__.py
nodestream_akamai/appsec_coverage/appsec_coverage.py
nodestream_akamai/cloudlets/__init__.py
nodestream_akamai/cloudlets/cloudlets.py
nodestream_akamai/cloudlets.yaml
nodestream_akamai/cpcodes/__init__.py
nodestream_akamai/cpcodes/cpcodes.py
nodestream_akamai/cpcodes.yaml
nodestream_akamai/cps/__init__.py
nodestream_akamai/cps/cps.py
nodestream_akamai/cps.yaml
nodestream_akamai/edgeworkers/__init__.py
nodestream_akamai/edgeworkers/edgeworkers.py
nodestream_akamai/edgeworkers.yaml
nodestream_akamai/edns/__init__.py
nodestream_akamai/edns/edns.py
nodestream_akamai/edns.yaml
nodestream_akamai/ehn/__init__.py
nodestream_akamai/ehn/ehn.py
nodestream_akamai/ehn.yaml
nodestream_akamai/examples/edns.json
nodestream_akamai/gtm/__init__.py
nodestream_akamai/gtm/gtm.py
nodestream_akamai/gtm.yaml
nodestream_akamai/iam-clients.yaml
nodestream_plugin_akamai-0.14.4.dist-info/LICENSE
nodestream_plugin_akamai-0.14.4.dist-info/METADATA
nodestream_plugin_akamai-0.14.4.dist-info/WHEEL
nodestream_plugin_akamai-0.14.4.dist-info/entry_points.txt
nodestream_plugin_akamai-0.14.4.dist-info/RECORD
