Metadata-Version: 2.3
Name: nodestream-plugin-akamai
Version: 0.14.4
Summary: Pipeline Plugin for Akamai Data
Author: Zach Probst
Author-email: Zach_Probst@intuit.com
Requires-Python: >=3.11,<4.0
Classifier: Programming Language :: Python :: 3
Classifier: Programming Language :: Python :: 3.11
Classifier: Programming Language :: Python :: 3.12
Classifier: Programming Language :: Python :: 3.13
Requires-Dist: edgegrid-python (>=1.2.1,<2.0.0)
Requires-Dist: jsonpath-ng (>=1.5.3,<2.0.0)
Requires-Dist: nodestream (>=0.14.0,<0.15.0)
Requires-Dist: requests (>=2.32.4,<3.0.0)
Requires-Dist: urllib3 (>=2.5.0,<3.0.0)
